csa_prediction_engine/__init__.py
csa_prediction_engine/api_client.py
csa_prediction_engine/version.py
csa_prediction_engine/bin/__init__.py
csa_prediction_engine/bin/_workers.py
csa_prediction_engine/bin/single_tasks.py
csa_prediction_engine/helpers/__init__.py
csa_prediction_engine/helpers/_auth_manager.py
csa_prediction_engine/helpers/_details_handler.py
csa_prediction_engine/helpers/_payload_handler.py
csa_prediction_engine/helpers/_postmaster.py
csa_prediction_engine/helpers/_router.py
csa_prediction_engine/parallel/__init__.py
csa_prediction_engine/parallel/_dispatchers.py
csa_prediction_engine/parallel/_threaded_predictions.py
csa_prediction_engine/parallel/_workers.py
csa_prediction_engine-2.2.5.dist-info/METADATA
csa_prediction_engine-2.2.5.dist-info/WHEEL
csa_prediction_engine-2.2.5.dist-info/top_level.txt
csa_prediction_engine-2.2.5.dist-info/RECORD
