Metadata-Version: 2.4
Name: csa_prediction_engine
Version: 2.2.5
Summary: The csa_prediction_engine library provides a suite of tools and functions for performing relevance-based predictions using the Cambridge Sports Analytics Prediction Engine API. The package is designed to facilitate single and multi-task predictions, allowing for flexible model evaluation and experimentation.
Author: Cambridge Sports Analytics
Author-email: prediction@csanalytics.io
Requires-Dist: numpy>=2.1
Requires-Dist: requests
Requires-Dist: csa_common_lib>=2.2.5
Dynamic: author
Dynamic: author-email
Dynamic: description
Dynamic: description-content-type
Dynamic: requires-dist
Dynamic: summary
